{"ARN":"Arnesby","ADZ":"Ashby de la Zouch","ASW":"Ashwell","ATH":"Atherstone","BHI":"Bardon Hill","BUO":"Barrow On Soar","BRL":"Barwell","BIB":"Binbrook","BIT":"Birstall","BCF":"Blackfordby","ZTT":"Bottesford","BXQ":"Braunstone","BTA":"Broughton Astley","CDB":"Cadeby","CAD":"Castle Donington","COA":"Coalville","OET":"Coleorton","CXY":"Cosby","CRL":"Croft","DES":"Desford","EMA":"East Midlands Apt","ELO":"Ellistown","ELH":"Elmesthorpe","EDB":"Enderby","FXF":"Foxton","FOW":"Frisby on the Wreake","GLF":"Glenfield","HEE":"Hethel","HIL":"Hinckley","HXO":"Hoton","TCK":"Ibstock","ILH":"Illston on the Hill","KWO":"Kegworth","KMO":"Kirby Muxloe","LCS":"Leicester","LOU":"Loughborough","LUN":"Lount","LTT":"Lutterworth","MBT":"Market Bosworth","MKH":"Market Harborough","MSA":"Measham","MBY":"Melton Mowbray","MQR":"Moira","NBG":"Narborough","NAT":"Normanton","NLF":"North Luffenham","XOA":"Oadby","OKM":"Oakham","ODL":"Old Dalby","OGP":"Osgathorpe","QBG":"Queniborough","SAL":"Saltby","SRW":"Shardlow","SPD":"Shepshed","SLY":"Sileby","SLW":"Slawston","SRB":"Somerby","SPL":"Stapleton","ESE":"Swestern","SYS":"Syston","TMS":"Thurmaston","THL":"Tilton on the Hill","WSO":"Whetstone","WWI":"Whitwick","WGS":"Wigston"}