{"ABI":"Aubiet","AUC":"Auch","AJC":"Avensac","AGN":"Ayguetinte","BCR":"Beaucaire","BLQ":"Blanquefort","NED":"Bretagne d'Armagnac","CPD":"Campagne-d'Armagnac","ZZA":"Castelnau-Dauzan","GVG":"Castera-Verduzan","TXX":"Castex","XCX":"Castex d'Armagnac","CZC":"Cazaubon","COD":"Condom","URF":"Courrensan","EAZ":"Eauze","FLU":"Fleurance","FRG":"Fources","GIM":"Gimont","GND":"Gondrin","REX":"Labarthete","LHN":"Lagarde-Hachan","PGL":"Lagraulet-du-Gers","WLJ":"Lannemaignan","WLK":"Lannepax","XEE":"Laree","LRM":"La Romieu","XSS":"Larroque sur l'Osse","LJZ":"Laujuzan","LU4":"Lauraet","HGA":"Le Houga","SKE":"L'Isle de Noe","LJN":"L'Isle-Jourdain","MC2":"Manciet","GJD":"Maul\u00e9on-d'Armagnac","ZMJ":"Mauvezin","MJK":"Mirande","MPX":"Mirepoix","MPV":"Monferran-Plav\u00e8s","YUP":"Monguilhem","MOA":"Mont\u00e9gut-Arros","OSG":"Montestruc-sur-Gers","MUU":"Montestruc-sur-Gers","GGZ":"Montr\u00e9al du Gers","NRO":"Nogaro","PJR":"Panjas","RZZ":"Ramouzens","QJK":"R\u00e9ans","ONJ":"Rejaumont","RIS":"Riscle","QJE":"Roquelaure","RQV":"Roques","SJP":"Saint-Jean-Poutge","GXG":"Sarragachies","SEG":"S\u00e9goufielle","ORB":"Sorbets","ZHI":"St-Clar","PYT":"Ste-Christie","IMC":"Ste-Christie-d'Armagnac","TGE":"St Germ\u00e9","TMO":"St Mont","YPZ":"St Puy","HT8":"Vic Fezensac"}